LICENSE
MANIFEST.in
README.md
setup.py
libpythonpro_gb/__init__.py
libpythonpro_gb/github_api.py
libpythonpro_gb.egg-info/PKG-INFO
libpythonpro_gb.egg-info/SOURCES.txt
libpythonpro_gb.egg-info/dependency_links.txt
libpythonpro_gb.egg-info/not-zip-safe
libpythonpro_gb.egg-info/requires.txt
libpythonpro_gb.egg-info/top_level.txt